{
    "id": "0xp9adqaRe",
    "userId": "102305825690200373955-google",
    "createdAt": "2016-09-17 16:42:57",
    "updatedAt": "2016-09-17 16:42:57",
    "title": "Белая гвардия",
    "author": "Михаил Афанасьевич Булгаков",
    "readDay": "30",
    "readMonth": "8",
    "readYear": "2016",
    "notes": "В романе-реквиеме автор описывает процесс разрушения мира русской интеллигенции.\n\n«Целых лет двадцать человек занимается каким-нибудь делом, например читает римское право, а на двадцать первом - вдруг оказывается, что римское право ни при чем, что он даже не понимает его и не любит, а на самом деле он тонкий садовод и горит любовью к цветам. Происходит это, надо полагать, от несовершенства нашего социального строя, при котором сплошь и рядом попадают на своё место только к концу жизни. »"
}