{
    "pZ2ElPhkBV": {
        "id": "pZ2ElPhkBV",
        "title": "Убить пересмешника",
        "author": "Ли Харпер",
        "notes": "",
        "createdAt": "2020-12-07 12:41:14",
        "user": {
            "id": "3448154788585127-facebook",
            "nickname": "Пу_тем",
            "booksCount": 7
        }
    },
    "_u6DwMGMwj": {
        "id": "_u6DwMGMwj",
        "title": "Таблетка от страха. Универсальные правила",
        "author": "Андрей Курпатов",
        "notes": "",
        "createdAt": "2020-12-06 21:45:56",
        "user": {
            "id": "202248233-vkontakte",
            "nickname": "zAAz",
            "booksCount": 75
        }
    },
    "hD5KT9r1iJ": {
        "id": "hD5KT9r1iJ",
        "title": "Кладбище домашних животных",
        "author": "Кинг Стивен",
        "notes": "",
        "createdAt": "2020-12-06 18:06:55",
        "user": {
            "id": "3448154788585127-facebook",
            "nickname": "Пу_тем",
            "booksCount": 6
        }
    },
    "ao99S2GMgc": {
        "id": "ao99S2GMgc",
        "title": "Приключения Гарретта 1. Сладкозвучный серебряный блюз",
        "author": "Глен Кук",
        "notes": "",
        "createdAt": "2020-12-06 15:51:00",
        "user": {
            "id": "118049897850017649660-googleplus",
            "nickname": "Sky",
            "booksCount": 183
        }
    },
    "5O6A1g7aui": {
        "id": "5O6A1g7aui",
        "title": "Дальняя дорога",
        "author": "Николас Спракс",
        "notes": "8",
        "createdAt": "2020-12-06 12:57:13",
        "user": {
            "id": "73323849-yandex",
            "nickname": "inna.besprozvannykh",
            "booksCount": 75
        }
    },
    "kXdT0N4lbN": {
        "id": "kXdT0N4lbN",
        "title": "Богатей",
        "author": "Ицхак Пинтосевмч",
        "notes": "Книга о секретах богатства. Перечитаю ещё раз",
        "createdAt": "2020-12-06 05:30:35",
        "user": {
            "id": "111367585493471720963-google",
            "nickname": "Fenix",
            "booksCount": 10
        }
    },
    "THeCkzgAvx": {
        "id": "THeCkzgAvx",
        "title": "Интроверты",
        "author": "Сьюзан Кейн",
        "notes": "",
        "createdAt": "2020-12-06 01:07:39",
        "user": {
            "id": "334696193054530347-mailru",
            "nickname": "Даша",
            "booksCount": 58
        }
    },
    "8TbcmBtQXg": {
        "id": "8TbcmBtQXg",
        "title": "Мистерии",
        "author": "Гамсун Кнут",
        "notes": "",
        "createdAt": "2020-12-05 14:36:21",
        "user": {
            "id": "108113656204404967440-google",
            "nickname": "Janet",
            "booksCount": 833
        }
    },
    "Q54QWAkeaT": {
        "id": "Q54QWAkeaT",
        "title": "ол",
        "author": "ол",
        "notes": "",
        "createdAt": "2020-12-05 12:41:53",
        "user": {
            "id": "46242783-vkontakte",
            "nickname": "ellikiper72",
            "booksCount": 2
        }
    },
    "3NAJGBGus-": {
        "id": "3NAJGBGus-",
        "title": "Вопрос о виновности. О политической ответственности Германии",
        "author": "Карл Ясперс",
        "notes": "6/10 Виновность каждого гражданина моральная, метафизическая, политическая и уголовная.",
        "createdAt": "2020-12-05 12:17:43",
        "user": {
            "id": "829893410524253-facebook",
            "nickname": "Daria Varyvod",
            "booksCount": 157
        }
    },
    "vl8UVQ1EX_": {
        "id": "vl8UVQ1EX_",
        "title": "Записки сумасшедшего",
        "author": "Николай Васильевич Гоголь",
        "notes": "",
        "createdAt": "2020-12-05 06:20:46",
        "user": {
            "id": "112388384595246311466-google",
            "nickname": "ЗаяцЛис",
            "booksCount": 113
        }
    },
    "wEFWjZ2Gat": {
        "id": "wEFWjZ2Gat",
        "title": "Цветы для Элджернона",
        "author": "Дэниел Киз",
        "notes": "Книга эмоционально поразила меня",
        "createdAt": "2020-12-04 20:41:19",
        "user": {
            "id": "10202544960024508-facebook",
            "nickname": "Beaviska",
            "booksCount": 44
        }
    },
    "MPWIMZgvSI": {
        "id": "MPWIMZgvSI",
        "title": "Список Шиндлера",
        "author": "",
        "notes": "8/10 Опис Голокосту у Польщі та роль Праведників світу.",
        "createdAt": "2020-12-04 09:16:38",
        "user": {
            "id": "829893410524253-facebook",
            "nickname": "Daria Varyvod",
            "booksCount": 156
        }
    },
    "dweaz2rSed": {
        "id": "dweaz2rSed",
        "title": "Гарри Поттер и философский камень",
        "author": "",
        "notes": "",
        "createdAt": "2020-12-03 20:57:32",
        "user": {
            "id": "139338401-vkontakte",
            "nickname": "sab_olya",
            "booksCount": 94
        }
    },
    "o4-ivxIYVz": {
        "id": "o4-ivxIYVz",
        "title": "Меч, дорога и удача",
        "author": "Алекс Орлов",
        "notes": "4/10 Боевое фєтези с єлементами дороги. Ничего цепляющего.",
        "createdAt": "2020-12-03 18:38:01",
        "user": {
            "id": "829893410524253-facebook",
            "nickname": "Daria Varyvod",
            "booksCount": 155
        }
    },
    "OXefQuMVe6": {
        "id": "OXefQuMVe6",
        "title": "Тёмная сторона",
        "author": "Макс Фрай",
        "notes": "",
        "createdAt": "2020-12-03 16:19:45",
        "user": {
            "id": "58602788-vkontakte",
            "nickname": "Dandelion_Wine",
            "booksCount": 55
        }
    },
    "ssDDE1Wq00": {
        "id": "ssDDE1Wq00",
        "title": "Астролог",
        "author": "Марк Алданов",
        "notes": "",
        "createdAt": "2020-12-03 10:34:04",
        "user": {
            "id": "15706320-vkontakte",
            "nickname": "borodach",
            "booksCount": 230
        }
    },
    "YDw7UmFWs3": {
        "id": "YDw7UmFWs3",
        "title": "Доссадийский эксперимент",
        "author": "Фрэнк Герберт",
        "notes": "",
        "createdAt": "2020-12-03 08:01:00",
        "user": {
            "id": "100002563462782-facebook",
            "nickname": "HXT",
            "booksCount": 396
        }
    },
    "-gJEGACA5R": {
        "id": "-gJEGACA5R",
        "title": "Отцы и дети",
        "author": "Иван Сергеевич Тургенев",
        "notes": "",
        "createdAt": "2020-12-02 20:42:54",
        "user": {
            "id": "112388384595246311466-google",
            "nickname": "ЗаяцЛис",
            "booksCount": 112
        }
    },
    "r4qyUYpdCE": {
        "id": "r4qyUYpdCE",
        "title": "Три инстинкта: жизнь, власть, секс. Универсальные правила",
        "author": "Андрей Курпатов",
        "notes": "",
        "createdAt": "2020-12-02 13:19:40",
        "user": {
            "id": "202248233-vkontakte",
            "nickname": "zAAz",
            "booksCount": 74
        }
    },
    "Ii-g0oSpAo": {
        "id": "Ii-g0oSpAo",
        "title": "Братья Карамазовы",
        "author": "Федор Достоевский",
        "notes": "",
        "createdAt": "2020-12-02 11:32:15",
        "user": {
            "id": "15706320-vkontakte",
            "nickname": "borodach",
            "booksCount": 229
        }
    },
    "KHwwzmo-Cp": {
        "id": "KHwwzmo-Cp",
        "title": "Мечтают ли андроиды об электроовцах?",
        "author": "Филип Киндред Дик",
        "notes": "",
        "createdAt": "2020-12-01 04:11:35",
        "user": {
            "id": "183883842-vkontakte",
            "nickname": "chaffeepwnz",
            "booksCount": 5
        }
    },
    "ZaA2jozz7h": {
        "id": "ZaA2jozz7h",
        "title": "Ведьмак: час призрения",
        "author": "Анджей Сапковский",
        "notes": "",
        "createdAt": "2020-12-01 04:10:54",
        "user": {
            "id": "183883842-vkontakte",
            "nickname": "chaffeepwnz",
            "booksCount": 4
        }
    },
    "Z6S_txHDxc": {
        "id": "Z6S_txHDxc",
        "title": "Ведьмак: кровь эльфов",
        "author": "Анджей Сапковский",
        "notes": "",
        "createdAt": "2020-12-01 04:10:36",
        "user": {
            "id": "183883842-vkontakte",
            "nickname": "chaffeepwnz",
            "booksCount": 3
        }
    },
    "K1wgybi_Jb": {
        "id": "K1wgybi_Jb",
        "title": "Ведьмак: меч предназначения",
        "author": "Анджей Сапковский",
        "notes": "",
        "createdAt": "2020-12-01 04:10:08",
        "user": {
            "id": "183883842-vkontakte",
            "nickname": "chaffeepwnz",
            "booksCount": 2
        }
    },
    "xh3Fj1Jood": {
        "id": "xh3Fj1Jood",
        "title": "Ведьмак: последнее желание",
        "author": "Анджей Сапковский",
        "notes": "",
        "createdAt": "2020-12-01 04:09:44",
        "user": {
            "id": "183883842-vkontakte",
            "nickname": "chaffeepwnz",
            "booksCount": 1
        }
    },
    "YQUi46W3qM": {
        "id": "YQUi46W3qM",
        "title": "Уролога.нет",
        "author": "Оганес Диланян",
        "notes": "",
        "createdAt": "2020-12-01 02:57:37",
        "user": {
            "id": "104690883692185089260-google",
            "nickname": "Йолант",
            "booksCount": 273
        }
    },
    "HhyEG8AYQE": {
        "id": "HhyEG8AYQE",
        "title": "Самолёт по имени Серёжка",
        "author": "Владислав Крапивин",
        "notes": "",
        "createdAt": "2020-12-01 02:57:00",
        "user": {
            "id": "104690883692185089260-google",
            "nickname": "Йолант",
            "booksCount": 272
        }
    },
    "-rvoeHxPNN": {
        "id": "-rvoeHxPNN",
        "title": "Тобол. Много званых",
        "author": "А. Иванов",
        "notes": "",
        "createdAt": "2020-11-30 21:45:49",
        "user": {
            "id": "117392596378069249667-google",
            "nickname": "4apa",
            "booksCount": 70
        }
    },
    "TmAtPpWBc1": {
        "id": "TmAtPpWBc1",
        "title": "Магическая уборка",
        "author": "Мари Кондо",
        "notes": "",
        "createdAt": "2020-11-30 21:28:04",
        "user": {
            "id": "2096581563762610-facebook",
            "nickname": "Таньчик",
            "booksCount": 117
        }
    }
}