{
    "GUg-AxI1pN": {
        "id": "GUg-AxI1pN",
        "title": "Машина времени",
        "author": "Герберт Уэллс",
        "notes": "",
        "createdAt": "2020-08-24 19:54:29",
        "user": {
            "id": "104299837-vkontakte",
            "nickname": "nkot46",
            "booksCount": 2
        }
    },
    "WlsuEkbNL1": {
        "id": "WlsuEkbNL1",
        "title": "Инициал Д. 1 Том",
        "author": "Сюити Сигэно",
        "notes": "Аниме",
        "createdAt": "2020-08-24 19:50:52",
        "user": {
            "id": "104299837-vkontakte",
            "nickname": "nkot46",
            "booksCount": 1
        }
    },
    "yVtKFkuorZ": {
        "id": "yVtKFkuorZ",
        "title": "Король Лир",
        "author": "Уильям Шекспир",
        "notes": "",
        "createdAt": "2020-08-24 19:05:46",
        "user": {
            "id": "58602788-vkontakte",
            "nickname": "Dandelion_Wine",
            "booksCount": 49
        }
    },
    "ntquIE5uga": {
        "id": "ntquIE5uga",
        "title": "Тоска",
        "author": "Антон Павлович Чехов",
        "notes": "",
        "createdAt": "2020-08-24 18:58:18",
        "user": {
            "id": "112388384595246311466-google",
            "nickname": "ЗаяцЛис",
            "booksCount": 79
        }
    },
    "aRLYB7qDB_": {
        "id": "aRLYB7qDB_",
        "title": "Светлана",
        "author": "Василий Андреевич Жуковский",
        "notes": "",
        "createdAt": "2020-08-24 18:51:01",
        "user": {
            "id": "112388384595246311466-google",
            "nickname": "ЗаяцЛис",
            "booksCount": 78
        }
    },
    "rMU6S0p98Z": {
        "id": "rMU6S0p98Z",
        "title": "Война и мир",
        "author": "Лев Николаевич Толстой",
        "notes": "",
        "createdAt": "2020-08-24 18:12:16",
        "user": {
            "id": "112388384595246311466-google",
            "nickname": "ЗаяцЛис",
            "booksCount": 77
        }
    },
    "uaJjMTZ3qY": {
        "id": "uaJjMTZ3qY",
        "title": "Дэвид Копперфилд",
        "author": "Диккенс",
        "notes": "",
        "createdAt": "2020-08-24 17:52:36",
        "user": {
            "id": "326783541-vkontakte",
            "nickname": "Askaliya",
            "booksCount": 3
        }
    },
    "cNNUey3E_w": {
        "id": "cNNUey3E_w",
        "title": "Свои погремушки",
        "author": "Вильмонт Екатерина",
        "notes": "Почему главную героиню зовут Аглая или Злата? Т.е. с обычным именем ничего не светит?",
        "createdAt": "2020-08-24 15:26:45",
        "user": {
            "id": "105831994080785626680-google",
            "nickname": "Chiffi",
            "booksCount": 197
        }
    },
    "ij0mpzpkcg": {
        "id": "ij0mpzpkcg",
        "title": "Птицы его мечты",
        "author": "Вильмонт Екатерина",
        "notes": "Как обычно сказочка для взрослых женщин. Но очень красивый язык",
        "createdAt": "2020-08-24 15:25:10",
        "user": {
            "id": "105831994080785626680-google",
            "nickname": "Chiffi",
            "booksCount": 196
        }
    },
    "gxAKt4Isc_": {
        "id": "gxAKt4Isc_",
        "title": "Хроники Амбера",
        "author": "Желязны Роджер",
        "notes": "",
        "createdAt": "2020-08-24 15:23:39",
        "user": {
            "id": "105831994080785626680-google",
            "nickname": "Chiffi",
            "booksCount": 195
        }
    },
    "HlO02e4hri": {
        "id": "HlO02e4hri",
        "title": "Наша маленькая жизнь",
        "author": "Мария Метлицкая",
        "notes": "",
        "createdAt": "2020-08-23 18:12:44",
        "user": {
            "id": "2096581563762610-facebook",
            "nickname": "Таньчик",
            "booksCount": 98
        }
    },
    "nIALbuMhr1": {
        "id": "nIALbuMhr1",
        "title": "Здравствуйте, мистер Бог, это Анна",
        "author": "Финн",
        "notes": "",
        "createdAt": "2020-08-23 16:24:12",
        "user": {
            "id": "118158645037334943900-google",
            "nickname": "Антенка",
            "booksCount": 57
        }
    },
    "_dQWVhs9T_": {
        "id": "_dQWVhs9T_",
        "title": "Михаил Булгаков",
        "author": "Мастер и Маргаита",
        "notes": "",
        "createdAt": "2020-08-23 08:40:18",
        "user": {
            "id": "221759364-yandex",
            "nickname": "Vladasbook",
            "booksCount": 4
        }
    },
    "kAt7zQswQx": {
        "id": "kAt7zQswQx",
        "title": "Чужие",
        "author": "Дин Алан Фостер",
        "notes": "",
        "createdAt": "2020-08-23 05:03:47",
        "user": {
            "id": "196071655-vkontakte",
            "nickname": "afferens.lucem",
            "booksCount": 176
        }
    },
    "xb86mi7CHX": {
        "id": "xb86mi7CHX",
        "title": "Чужой",
        "author": "Дин Алан Фостер",
        "notes": "",
        "createdAt": "2020-08-23 05:03:20",
        "user": {
            "id": "196071655-vkontakte",
            "nickname": "afferens.lucem",
            "booksCount": 175
        }
    },
    "TYSZGGCO75": {
        "id": "TYSZGGCO75",
        "title": "Джек Лондон",
        "author": "Сказание о Кише",
        "notes": "",
        "createdAt": "2020-08-23 04:24:16",
        "user": {
            "id": "221759364-yandex",
            "nickname": "Vladasbook",
            "booksCount": 3
        }
    },
    "CfPhoYZuwW": {
        "id": "CfPhoYZuwW",
        "title": "Первый учитель. (Повесть).",
        "author": "Чингиз Айтматов",
        "notes": "",
        "createdAt": "2020-08-23 03:49:20",
        "user": {
            "id": "221759364-yandex",
            "nickname": "Vladasbook",
            "booksCount": 2
        }
    },
    "2TtmCirUAK": {
        "id": "2TtmCirUAK",
        "title": "Сказание о Кише",
        "author": "Джек Лондон",
        "notes": "",
        "createdAt": "2020-08-23 03:30:31",
        "user": {
            "id": "221759364-yandex",
            "nickname": "Vladasbook",
            "booksCount": 1
        }
    },
    "LY8GqMwYj1": {
        "id": "LY8GqMwYj1",
        "title": "Ослокрады",
        "author": "Джеральд Даррелл",
        "notes": "",
        "createdAt": "2020-08-22 15:10:30",
        "user": {
            "id": "118049897850017649660-googleplus",
            "nickname": "Sky",
            "booksCount": 173
        }
    },
    "nnA4SnJxtZ": {
        "id": "nnA4SnJxtZ",
        "title": "Шамайка",
        "author": "Юрий Коваль",
        "notes": "",
        "createdAt": "2020-08-22 15:08:47",
        "user": {
            "id": "118049897850017649660-googleplus",
            "nickname": "Sky",
            "booksCount": 172
        }
    },
    "KtaCf_t70d": {
        "id": "KtaCf_t70d",
        "title": "Искусство любить",
        "author": "Эрих Фромм",
        "notes": "",
        "createdAt": "2020-08-22 14:45:10",
        "user": {
            "id": "202248233-vkontakte",
            "nickname": "zAAz",
            "booksCount": 63
        }
    },
    "uHsJon5Cch": {
        "id": "uHsJon5Cch",
        "title": "Простые волшебные вещи",
        "author": "Макс Фрай",
        "notes": "Надо же! Всего каких-то сто лет назад этот мальчик торжественно клялся, что вообще не будет спать, когда вырастет. (с) матушка Мелифаро\nМне пришлось перейти на галоп, чтобы догнать неугомонного господина Почтеннейшего Начальника, скатившегося вниз, в гостиную, по перилам. Любимый спорт младших школьников и злых колдунов.\nУ меня появилась хорошая возможность отпустить домой симпатичного капитана Гьяту и заодно помочь своему приятелю Андэ на собственном опыте уяснить, что сбывшаяся мечта далеко не всегда тождественна счастью.\nВы не впиливаете, Макс. Я уезжаю навсегда, и вообще все всегда уезжают навсегда. Вернуться невозможно - вместо нас всегда возвращается кто-то другой, но это никто не впиливает. (с) Андэ Пу",
        "createdAt": "2020-08-21 18:29:36",
        "user": {
            "id": "58602788-vkontakte",
            "nickname": "Dandelion_Wine",
            "booksCount": 48
        }
    },
    "SAeL89gZ6u": {
        "id": "SAeL89gZ6u",
        "title": "Чудовища доктора Эйнштейна",
        "author": "Крис Импи",
        "notes": "",
        "createdAt": "2020-08-21 13:20:26",
        "user": {
            "id": "117392596378069249667-google",
            "nickname": "4apa",
            "booksCount": 61
        }
    },
    "Jifj1o_JFd": {
        "id": "Jifj1o_JFd",
        "title": "Близость",
        "author": "Ошо",
        "notes": "Хорошая книга о философии жизни. Много про то, что не надо бежать впереди жизни, нужно научится ценить моменты, быть мягкими и гибкими и открываться миру несмотря ни на что. Сейчас так редко мы позволяем жизни просто течь, без цели, без смысла, просто жить, наслаждаясь моментом",
        "createdAt": "2020-08-21 10:46:28",
        "user": {
            "id": "254448176-yandex",
            "nickname": "Len4e91",
            "booksCount": 9
        }
    },
    "Xoy0KgsKjq": {
        "id": "Xoy0KgsKjq",
        "title": "Беспокойная юность",
        "author": "Паустовский К.Г.",
        "notes": "Книга 2, Повесть о жизни",
        "createdAt": "2020-08-20 17:32:20",
        "user": {
            "id": "100599204551896265722-google",
            "nickname": "exulted",
            "booksCount": 131
        }
    },
    "4bwvAv_O9C": {
        "id": "4bwvAv_O9C",
        "title": "Последний герой",
        "author": "Пратчетт, Терри",
        "notes": "Скорее даже не рассказ, сага в прозе о Серебряной орде и их героическом спасении мира от конца света, который правда они сами и устроили",
        "createdAt": "2020-08-20 17:16:15",
        "user": {
            "id": "115753719718250012620-google",
            "nickname": "Garka",
            "booksCount": 260
        }
    },
    "oFkl_aPhoF": {
        "id": "oFkl_aPhoF",
        "title": "Вор времени",
        "author": "Пратчет, Терри",
        "notes": "Немного фентези, немного философии, немного квантовой физики. Классная книга, Смерть великолепен",
        "createdAt": "2020-08-20 17:13:33",
        "user": {
            "id": "115753719718250012620-google",
            "nickname": "Garka",
            "booksCount": 259
        }
    },
    "nyqvP-8wEN": {
        "id": "nyqvP-8wEN",
        "title": "Дорога на две улицы",
        "author": "Мария Метлицкая",
        "notes": "",
        "createdAt": "2020-08-19 18:07:27",
        "user": {
            "id": "2096581563762610-facebook",
            "nickname": "Таньчик",
            "booksCount": 97
        }
    },
    "90OGZm1_up": {
        "id": "90OGZm1_up",
        "title": "",
        "author": "зыгарь",
        "notes": "",
        "createdAt": "2020-08-17 12:48:28",
        "user": {
            "id": "14490047-vkontakte",
            "nickname": "christo_redemptor",
            "booksCount": 1
        }
    },
    "sI5FqjXtGJ": {
        "id": "sI5FqjXtGJ",
        "title": "Ошибка молодости",
        "author": "Мария Метлицкая",
        "notes": "",
        "createdAt": "2020-08-17 06:49:28",
        "user": {
            "id": "2096581563762610-facebook",
            "nickname": "Таньчик",
            "booksCount": 96
        }
    }
}