{
    "8BFYjAIEcl": {
        "id": "8BFYjAIEcl",
        "title": "Расмус, Понтус и Растяпа",
        "author": "Астрид Линдгрен",
        "notes": "",
        "createdAt": "2021-10-25 08:58:38",
        "user": {
            "id": "2429115410558517-facebook",
            "nickname": null,
            "booksCount": 11
        }
    },
    "6Oe89B90G-": {
        "id": "6Oe89B90G-",
        "title": "Волшебник Изумрудного города",
        "author": "Александр Волков",
        "notes": "",
        "createdAt": "2021-10-25 08:58:31",
        "user": {
            "id": "2429115410558517-facebook",
            "nickname": null,
            "booksCount": 10
        }
    },
    "HaIu3HXFna": {
        "id": "HaIu3HXFna",
        "title": "Чарли и шоколадная фабрика",
        "author": "Роальд Даль",
        "notes": "",
        "createdAt": "2021-10-25 08:58:25",
        "user": {
            "id": "2429115410558517-facebook",
            "nickname": null,
            "booksCount": 9
        }
    },
    "pnTSMEZUHD": {
        "id": "pnTSMEZUHD",
        "title": "Капитан Сорви-голова",
        "author": "Валерий Медведев",
        "notes": "",
        "createdAt": "2021-10-25 08:58:09",
        "user": {
            "id": "2429115410558517-facebook",
            "nickname": null,
            "booksCount": 8
        }
    },
    "TCuFCc1P3I": {
        "id": "TCuFCc1P3I",
        "title": "Рассказы",
        "author": "Николай Носов",
        "notes": "",
        "createdAt": "2021-10-25 08:57:56",
        "user": {
            "id": "2429115410558517-facebook",
            "nickname": null,
            "booksCount": 7
        }
    },
    "ayCpL0Dad6": {
        "id": "ayCpL0Dad6",
        "title": "Алиса в Зазеркалье",
        "author": "Льюис Кэрролл",
        "notes": "",
        "createdAt": "2021-10-25 08:57:36",
        "user": {
            "id": "2429115410558517-facebook",
            "nickname": null,
            "booksCount": 6
        }
    },
    "OWW56SG6uT": {
        "id": "OWW56SG6uT",
        "title": "Алиса в Стране чудес",
        "author": "Льюис Кэрролл",
        "notes": "",
        "createdAt": "2021-10-25 08:57:14",
        "user": {
            "id": "2429115410558517-facebook",
            "nickname": null,
            "booksCount": 5
        }
    },
    "CD9Q70peWg": {
        "id": "CD9Q70peWg",
        "title": "Как собрать автомобиль",
        "author": "Мартин Содомка",
        "notes": "",
        "createdAt": "2021-10-25 08:57:03",
        "user": {
            "id": "2429115410558517-facebook",
            "nickname": null,
            "booksCount": 4
        }
    },
    "Lk57Id7pCn": {
        "id": "Lk57Id7pCn",
        "title": "Как собрать мотоцикл",
        "author": "Мартин Содомка",
        "notes": "",
        "createdAt": "2021-10-25 08:56:46",
        "user": {
            "id": "2429115410558517-facebook",
            "nickname": null,
            "booksCount": 3
        }
    },
    "I26OWFtJHP": {
        "id": "I26OWFtJHP",
        "title": "В Стране невыученных уроков",
        "author": "Лия Гераскина",
        "notes": "",
        "createdAt": "2021-10-25 08:56:28",
        "user": {
            "id": "2429115410558517-facebook",
            "nickname": null,
            "booksCount": 2
        }
    },
    "5Zd-8VJdIq": {
        "id": "5Zd-8VJdIq",
        "title": "Незнайка в Солнечном городе",
        "author": "Николай Носов",
        "notes": "",
        "createdAt": "2021-10-25 08:56:10",
        "user": {
            "id": "2429115410558517-facebook",
            "nickname": null,
            "booksCount": 1
        }
    },
    "XbHGezfFIZ": {
        "id": "XbHGezfFIZ",
        "title": "Фаворит 1",
        "author": "Валентин Пикуль",
        "notes": "",
        "createdAt": "2021-10-25 08:34:37",
        "user": {
            "id": "101113826695860472422-google",
            "nickname": null,
            "booksCount": 2
        }
    },
    "qgvglZ8OYz": {
        "id": "qgvglZ8OYz",
        "title": "Sapiens.Краткая история человечества",
        "author": "Юваль Ной",
        "notes": "",
        "createdAt": "2021-10-25 08:33:12",
        "user": {
            "id": "101113826695860472422-google",
            "nickname": null,
            "booksCount": 1
        }
    },
    "MpAwArNTl3": {
        "id": "MpAwArNTl3",
        "title": "Гвенди и её шкатулка",
        "author": "Стивен Кинг",
        "notes": "",
        "createdAt": "2021-10-24 23:37:39",
        "user": {
            "id": "94738840-vkontakte",
            "nickname": "Mad Wolf",
            "booksCount": 250
        }
    },
    "DEoXcRLTiH": {
        "id": "DEoXcRLTiH",
        "title": "Ось іде людина",
        "author": "Александр Ґранах",
        "notes": "7/10 Автобіографія актора з маленького єврейского містечка.",
        "createdAt": "2021-10-24 18:52:53",
        "user": {
            "id": "829893410524253-facebook",
            "nickname": "Daria Varyvod",
            "booksCount": 217
        }
    },
    "xCHxk9WgdT": {
        "id": "xCHxk9WgdT",
        "title": "О дивный новый мир",
        "author": "Олдос Хаксли",
        "notes": "",
        "createdAt": "2021-10-23 20:46:20",
        "user": {
            "id": "112090473416384685204-google",
            "nickname": "Cr_RONIN",
            "booksCount": 2
        }
    },
    "eBq9KEmYzf": {
        "id": "eBq9KEmYzf",
        "title": "Сидхартха",
        "author": "Герман Гессе",
        "notes": "",
        "createdAt": "2021-10-23 20:45:25",
        "user": {
            "id": "112090473416384685204-google",
            "nickname": "Cr_RONIN",
            "booksCount": 1
        }
    },
    "-N6iVvPa45": {
        "id": "-N6iVvPa45",
        "title": "Дело о катящихся костях",
        "author": "Эрл Стэнли Гарднер",
        "notes": "",
        "createdAt": "2021-10-23 17:37:32",
        "user": {
            "id": "108113656204404967440-google",
            "nickname": "Janet",
            "booksCount": 891
        }
    },
    "OMqTyNsHVF": {
        "id": "OMqTyNsHVF",
        "title": "Невеста для князя",
        "author": "Ольга Истомина",
        "notes": "",
        "createdAt": "2021-10-23 13:31:10",
        "user": {
            "id": "193697993-vkontakte",
            "nickname": "butercupa",
            "booksCount": 20
        }
    },
    "UgwPAstzEx": {
        "id": "UgwPAstzEx",
        "title": "Бог как иллюзия",
        "author": "Ричард Докинз",
        "notes": "",
        "createdAt": "2021-10-22 08:14:22",
        "user": {
            "id": "73323849-yandex",
            "nickname": "inna.besprozvannykh",
            "booksCount": 76
        }
    },
    "gdxwlb9W9k": {
        "id": "gdxwlb9W9k",
        "title": "Прогулка Самый простой источник радости и смысла",
        "author": "Эрлинг Кагге",
        "notes": "",
        "createdAt": "2021-10-21 16:47:39",
        "user": {
            "id": "30558181-vkontakte",
            "nickname": "EsterHani",
            "booksCount": 217
        }
    },
    "cgmNJZMbZO": {
        "id": "cgmNJZMbZO",
        "title": "Кельтские мифы От Короля Артура и Дейрдре до фейри и друидов",
        "author": "Миранда Олдхаус-Грин",
        "notes": "",
        "createdAt": "2021-10-21 16:46:03",
        "user": {
            "id": "30558181-vkontakte",
            "nickname": "EsterHani",
            "booksCount": 216
        }
    },
    "xNjUsJjOuF": {
        "id": "xNjUsJjOuF",
        "title": "Кельтские мифы От Короля Артура и Дейрдре до фейри и друидов",
        "author": "Миранда Олдхаус-Грин",
        "notes": "",
        "createdAt": "2021-10-21 16:44:30",
        "user": {
            "id": "181853639-yandex",
            "nickname": "sanya-sin2012",
            "booksCount": 1
        }
    },
    "ypDo_pjCPw": {
        "id": "ypDo_pjCPw",
        "title": "Мартин Иден",
        "author": "Джек Лондон",
        "notes": "Мне надоел до безумия. Ни слова о действительности",
        "createdAt": "2021-10-21 00:03:42",
        "user": {
            "id": "109787328219839805802-google",
            "nickname": "Rainbow",
            "booksCount": 84
        }
    },
    "6NOnlqUPoj": {
        "id": "6NOnlqUPoj",
        "title": "Дело о лжесвидетельстве попугая",
        "author": "Эрл Стэнли Гарднер",
        "notes": "",
        "createdAt": "2021-10-20 15:08:30",
        "user": {
            "id": "108113656204404967440-google",
            "nickname": "Janet",
            "booksCount": 890
        }
    },
    "q9Vbrpl4mI": {
        "id": "q9Vbrpl4mI",
        "title": "Дело о туфле магазинного воришки",
        "author": "Эрл Стэнли Гарднер",
        "notes": "",
        "createdAt": "2021-10-19 19:40:09",
        "user": {
            "id": "108113656204404967440-google",
            "nickname": "Janet",
            "booksCount": 889
        }
    },
    "EbQ6RuqlsH": {
        "id": "EbQ6RuqlsH",
        "title": "Характерник",
        "author": "Олексій Чорний, Дарця Зіронька",
        "notes": "3/10 Мальопис. Діч. Нічьо не понятно, темні кольори, цицьки.",
        "createdAt": "2021-10-19 14:30:51",
        "user": {
            "id": "829893410524253-facebook",
            "nickname": "Daria Varyvod",
            "booksCount": 216
        }
    },
    "ep3UjYbRJK": {
        "id": "ep3UjYbRJK",
        "title": "Игра в куклы",
        "author": "Магнус Йонссон",
        "notes": "",
        "createdAt": "2021-10-18 20:44:33",
        "user": {
            "id": "1537586159620888-facebook",
            "nickname": null,
            "booksCount": 54
        }
    },
    "DCdVAk0Dhr": {
        "id": "DCdVAk0Dhr",
        "title": "Дело о замене лица",
        "author": "Эрл Стэнли Гарднер",
        "notes": "",
        "createdAt": "2021-10-18 18:05:10",
        "user": {
            "id": "108113656204404967440-google",
            "nickname": "Janet",
            "booksCount": 888
        }
    },
    "fW_g3EIBLr": {
        "id": "fW_g3EIBLr",
        "title": "Очаровательный кишечник. Как самый могущественный орган управляет нами",
        "author": "Джулия Эндерс",
        "notes": "",
        "createdAt": "2021-10-18 17:31:21",
        "user": {
            "id": "112388384595246311466-google",
            "nickname": "ЗаяцЛис",
            "booksCount": 172
        }
    }
}