{
    "sMi_aFF6Kj": {
        "id": "sMi_aFF6Kj",
        "title": "Мужская логика 8-го Марта (рассказ)",
        "author": "Михалкова Елена",
        "notes": "Илюшин и Бабкин1.   зарабатывали на жизнь несложным физическим трудом с незначительными вкраплениями умственного....отшутилась, сказав, что врожденные комплексы не позволяют ей встречаться с мужчинами ниже ее ростом.....обладал характером романтического танка, то есть пер напролом, но с выдумкой, время от времени являя окружающим доброту характера и бескорыстие, чем ошеломлял их до глубины души.... А из положения жертвы так удобно управлять ситуацией – не правда ли",
        "createdAt": "2021-07-18 14:04:10",
        "user": {
            "id": "105831994080785626680-google",
            "nickname": "Chiffi",
            "booksCount": 293
        }
    },
    "3-lKW1lsQz": {
        "id": "3-lKW1lsQz",
        "title": "Тот, кто ловит мотыльков",
        "author": "Михалкова Елена",
        "notes": "В случа екстраординарных событий первым делом обеспечь свою безопасность. Затем-зафиксируй то, что видишь.",
        "createdAt": "2021-07-16 20:37:35",
        "user": {
            "id": "105831994080785626680-google",
            "nickname": "Chiffi",
            "booksCount": 292
        }
    },
    "XDTkVtNNUI": {
        "id": "XDTkVtNNUI",
        "title": "Лики времени",
        "author": "Александр Прасол",
        "notes": "",
        "createdAt": "2021-07-16 19:03:59",
        "user": {
            "id": "5175580462988229760-mailru",
            "nickname": "Triste",
            "booksCount": 29
        }
    },
    "BMCW1B9sEb": {
        "id": "BMCW1B9sEb",
        "title": "Чужой из теней",
        "author": "Тим Леббон",
        "notes": "Брошено. Скучно.",
        "createdAt": "2021-07-16 17:56:19",
        "user": {
            "id": "5175580462988229760-mailru",
            "nickname": "Triste",
            "booksCount": 28
        }
    },
    "rVlvZPhkZh": {
        "id": "rVlvZPhkZh",
        "title": "Бабочки полет",
        "author": "Кобаяси Исса, Басё",
        "notes": "",
        "createdAt": "2021-07-16 17:54:43",
        "user": {
            "id": "5175580462988229760-mailru",
            "nickname": "Triste",
            "booksCount": 27
        }
    },
    "MkHr3wGN3r": {
        "id": "MkHr3wGN3r",
        "title": "Торжество незначительности",
        "author": "Милан Кундера",
        "notes": "",
        "createdAt": "2021-07-16 17:49:14",
        "user": {
            "id": "5175580462988229760-mailru",
            "nickname": "Triste",
            "booksCount": 26
        }
    },
    "-xA7Y5sCAL": {
        "id": "-xA7Y5sCAL",
        "title": "Обезьяна",
        "author": "Рюноскэ Акутагава",
        "notes": "",
        "createdAt": "2021-07-16 17:48:31",
        "user": {
            "id": "5175580462988229760-mailru",
            "nickname": "Triste",
            "booksCount": 25
        }
    },
    "XgwjdHpkyx": {
        "id": "XgwjdHpkyx",
        "title": "Бататовая каша",
        "author": "Рюноскэ Акутагава",
        "notes": "",
        "createdAt": "2021-07-16 17:48:19",
        "user": {
            "id": "5175580462988229760-mailru",
            "nickname": "Triste",
            "booksCount": 24
        }
    },
    "FKYaT9bLhG": {
        "id": "FKYaT9bLhG",
        "title": "Нос",
        "author": "Рюноскэ Акутагава",
        "notes": "",
        "createdAt": "2021-07-16 17:48:04",
        "user": {
            "id": "5175580462988229760-mailru",
            "nickname": "Triste",
            "booksCount": 23
        }
    },
    "kGfLb8HBXM": {
        "id": "kGfLb8HBXM",
        "title": "Ад одиночества",
        "author": "Рюноскэ Акутагава",
        "notes": "",
        "createdAt": "2021-07-16 17:47:48",
        "user": {
            "id": "5175580462988229760-mailru",
            "nickname": "Triste",
            "booksCount": 22
        }
    },
    "WffG_nzXLO": {
        "id": "WffG_nzXLO",
        "title": "Ворота расёмон",
        "author": "Рюноскэ Акутагава",
        "notes": "",
        "createdAt": "2021-07-16 17:47:36",
        "user": {
            "id": "5175580462988229760-mailru",
            "nickname": "Triste",
            "booksCount": 21
        }
    },
    "PmuylMx7Dl": {
        "id": "PmuylMx7Dl",
        "title": "Юноши и смерть",
        "author": "Рюноскэ Акутагава",
        "notes": "",
        "createdAt": "2021-07-16 17:44:50",
        "user": {
            "id": "5175580462988229760-mailru",
            "nickname": "Triste",
            "booksCount": 20
        }
    },
    "bAlPRwLwPC": {
        "id": "bAlPRwLwPC",
        "title": "Морфий",
        "author": "Булгаков М.А.",
        "notes": "Любимая книга.",
        "createdAt": "2021-07-16 17:43:27",
        "user": {
            "id": "5175580462988229760-mailru",
            "nickname": "Triste",
            "booksCount": 19
        }
    },
    "cNQYirwy_W": {
        "id": "cNQYirwy_W",
        "title": "Повелители DOOM",
        "author": "Дэвид Кушнер",
        "notes": "",
        "createdAt": "2021-07-16 17:43:03",
        "user": {
            "id": "5175580462988229760-mailru",
            "nickname": "Triste",
            "booksCount": 18
        }
    },
    "-ZfWoFwjgx": {
        "id": "-ZfWoFwjgx",
        "title": "Джазовые портреты",
        "author": "Харуки Мураками",
        "notes": "",
        "createdAt": "2021-07-16 17:41:51",
        "user": {
            "id": "5175580462988229760-mailru",
            "nickname": "Triste",
            "booksCount": 17
        }
    },
    "UzJ4Dc3nYM": {
        "id": "UzJ4Dc3nYM",
        "title": "Поэма \"Реквием\"",
        "author": "А.А.Ахматова",
        "notes": "",
        "createdAt": "2021-07-16 17:41:00",
        "user": {
            "id": "5175580462988229760-mailru",
            "nickname": "Triste",
            "booksCount": 16
        }
    },
    "985Rw8ceEn": {
        "id": "985Rw8ceEn",
        "title": "Горе от ума",
        "author": "А.С.Грибоедов",
        "notes": "",
        "createdAt": "2021-07-16 17:39:58",
        "user": {
            "id": "5175580462988229760-mailru",
            "nickname": "Triste",
            "booksCount": 15
        }
    },
    "bvgo_kl0e2": {
        "id": "bvgo_kl0e2",
        "title": "Баллада \"Светлана\"",
        "author": "В.А.Жуковский",
        "notes": "",
        "createdAt": "2021-07-16 17:39:35",
        "user": {
            "id": "5175580462988229760-mailru",
            "nickname": "Triste",
            "booksCount": 14
        }
    },
    "uzkDP716k4": {
        "id": "uzkDP716k4",
        "title": "Слово о полку Игореве",
        "author": "",
        "notes": "",
        "createdAt": "2021-07-16 17:38:30",
        "user": {
            "id": "5175580462988229760-mailru",
            "nickname": "Triste",
            "booksCount": 13
        }
    },
    "KKk6xVUnll": {
        "id": "KKk6xVUnll",
        "title": "Недоросль",
        "author": "Д.И.Фонвизин",
        "notes": "",
        "createdAt": "2021-07-16 17:38:18",
        "user": {
            "id": "5175580462988229760-mailru",
            "nickname": "Triste",
            "booksCount": 12
        }
    },
    "cBxe82ZgRR": {
        "id": "cBxe82ZgRR",
        "title": "Гроза",
        "author": "А. Н. Островский",
        "notes": "",
        "createdAt": "2021-07-16 17:37:20",
        "user": {
            "id": "5175580462988229760-mailru",
            "nickname": "Triste",
            "booksCount": 11
        }
    },
    "1V3PPmjkOE": {
        "id": "1V3PPmjkOE",
        "title": "Евгений Онегин",
        "author": "А.С.Пушкин",
        "notes": "",
        "createdAt": "2021-07-16 17:36:24",
        "user": {
            "id": "5175580462988229760-mailru",
            "nickname": "Triste",
            "booksCount": 10
        }
    },
    "4eJ-RIE0fm": {
        "id": "4eJ-RIE0fm",
        "title": "Герой нашего времени",
        "author": "М.Ю.Лермонтов",
        "notes": "",
        "createdAt": "2021-07-16 17:35:39",
        "user": {
            "id": "5175580462988229760-mailru",
            "nickname": "Triste",
            "booksCount": 9
        }
    },
    "HKR-gzfklM": {
        "id": "HKR-gzfklM",
        "title": "Дама с собачкой",
        "author": "А.П.Чехов",
        "notes": "",
        "createdAt": "2021-07-16 17:34:07",
        "user": {
            "id": "5175580462988229760-mailru",
            "nickname": "Triste",
            "booksCount": 8
        }
    },
    "wAr7e5bqfN": {
        "id": "wAr7e5bqfN",
        "title": "Ионыч",
        "author": "А.П.Чехов",
        "notes": "",
        "createdAt": "2021-07-16 17:33:54",
        "user": {
            "id": "5175580462988229760-mailru",
            "nickname": "Triste",
            "booksCount": 7
        }
    },
    "tDiOAyIiZf": {
        "id": "tDiOAyIiZf",
        "title": "Вишнёвый сад",
        "author": "А.П.Чехов",
        "notes": "",
        "createdAt": "2021-07-16 17:33:31",
        "user": {
            "id": "5175580462988229760-mailru",
            "nickname": "Triste",
            "booksCount": 6
        }
    },
    "kaSCCah9qy": {
        "id": "kaSCCah9qy",
        "title": "Мастер и Маргарита",
        "author": "Ф.М.Достоевский",
        "notes": "",
        "createdAt": "2021-07-16 17:32:30",
        "user": {
            "id": "5175580462988229760-mailru",
            "nickname": "Triste",
            "booksCount": 6
        }
    },
    "2eEnQ5JhiX": {
        "id": "2eEnQ5JhiX",
        "title": "Все семь волн",
        "author": "Даниэль Глаттауэр",
        "notes": "",
        "createdAt": "2021-07-15 21:29:44",
        "user": {
            "id": "108113656204404967440-google",
            "nickname": "Janet",
            "booksCount": 868
        }
    },
    "tBsna8NNfx": {
        "id": "tBsna8NNfx",
        "title": "451 градус по фарингейту",
        "author": "Рей Бредбери",
        "notes": "",
        "createdAt": "2021-07-15 19:19:27",
        "user": {
            "id": "173160241-vkontakte",
            "nickname": "id_nastena_sazanovich",
            "booksCount": 2
        }
    },
    "IOGLYlWqJw": {
        "id": "IOGLYlWqJw",
        "title": "Вино из одуванчиков",
        "author": "Рей Бредбери",
        "notes": "",
        "createdAt": "2021-07-15 19:19:03",
        "user": {
            "id": "173160241-vkontakte",
            "nickname": "id_nastena_sazanovich",
            "booksCount": 1
        }
    }
}