{
    "id": "enGOmQR4U2",
    "userId": "109746193906459706720-google",
    "createdAt": "2022-01-03 13:30:58",
    "updatedAt": "2022-07-01 13:13:12",
    "title": "Магия Ранит. #1",
    "author": "Илона Эндрюс",
    "readDay": "1",
    "readMonth": "10",
    "readYear": "2021",
    "notes": "Наемница и свободный стрелок Кейт Дэниелс живет в мире, полном коварных существ и превращений. В городе, где с неба сыплются крылатые змеи, а прилив магии рушит небоскребы.\n\nКогда опекуна Кейт – рыцаря-прорицателя Грега Фелдмана – находят убитым, кажется, Атланта катится в преисподнюю… Возвращаться под защиту Ордена накануне 25-летия Кейт не хочет – спасибо ослиному упрямству и острому языку. Зато берется расследовать гибель прорицателя. Встречает союзников среди спятивших магов, сбрендивших оборотней и мошенников-некромантов. А заодно – красавца-мужчину с золотыми искорками в глазах…"
}