{
    "id": "RygEgVXQ-1",
    "userId": "109746193906459706720-google",
    "createdAt": "2022-04-20 11:27:16",
    "updatedAt": "2022-04-20 11:27:28",
    "title": "Первая невеста чернокнижника",
    "author": "Марина Ефиминюк",
    "readDay": "20",
    "readMonth": "4",
    "readYear": "2022",
    "notes": "Знаете, как это бывает? Живешь себе, радуешься, никого не трогаешь… а потом попадаешь. В прямом смысле этого слова. Попадаешь в темный замок, стоящий на границе миров. Хозяин славного места привлекательный и обходительный, мало что чернокнижник. Да и все жители подозрительно приветливые… как будто что-то скрывают. В общем, в гостях хорошо, но дома лучше! Никаких воскресших умертвий, черных гримуаров и тайных проклятий. Вернуться бы в родной мир, но только кто меня отпустит?"
}