{
    "id": "b6RQy5Pcf-",
    "userId": "333646551-vkontakte",
    "createdAt": "2020-04-07 13:15:57",
    "updatedAt": "2020-04-07 13:15:57",
    "title": "Пять четвертинок апельсина",
    "author": "Джоанн Харрис",
    "readDay": "7",
    "readMonth": "4",
    "readYear": "2020",
    "notes": "От матери в наследство Фрамбуаз получила альбом с кулинарными рецептами — негусто, если учесть, что ее брату Кассису досталась ферма, а старшей сестре Рен-Клод — винный погреб со всем содержимым. Но весь фокус в том, что на полях альбома, рядом с рецептами разных блюд и травяных снадобий, мать записывала свои мысли и признания относительно некоторых событий ее жизни — словом, вела своеобразный дневник. И в этом дневнике Фрамбуаз пытается найти ответы на мрачные загадки прошлого."
}