{
    "id": "HiygkmWFLs",
    "lang": "ru",
    "userId": "107127274479758647951-google",
    "createdAt": "2015-10-03 13:17:03",
    "updatedAt": "2015-10-03 13:17:03",
    "title": "Как жить дольше 50 лет: честный разговор с врачом о лекарствах и медицине",
    "author": "Мясников Александр",
    "readDay": "",
    "readMonth": "7",
    "readYear": "2015",
    "notes": "Популистская книга, но любопытно. Интересен описанный подход к формированию медико-экономических стандартов на основании больших накопленных массивов данных (США, страховая медицина). В остальном в плане подходов ничего нового (собственно ничего нового и не придумать, наверное), россыпь любопытных фактов."
}