{
    "id": "l0eXzMBrC4",
    "lang": "ru",
    "userId": "230448124-vkontakte",
    "createdAt": "2015-08-17 17:45:24",
    "updatedAt": "2015-08-17 17:45:24",
    "title": "Искатели ветра",
    "author": "Алексей Пехов",
    "readDay": "",
    "readMonth": "",
    "readYear": "",
    "notes": "Мир Хары утратил самое ценное – знание. Все, что тысячелетие назад было обыденным и привычным, теперь кажется сказкой. За жалкие крупицы великого искусства прошлого маги ведут кровопролитные войны. Самая страшная и беспощадная война вот уже пять веков длится между теми, кто правит миром, – Ходящими и Проклятыми. Тьма и свет, некромантия и целительство сплелись в смертельный тугой клубок, уничтожающий всех, кто посмеет к нему прикоснуться. Нэсс и Лаэн бросают вызов носителям Дара, чтобы спасти свою жизнь. Что станет ставкой в их игре – совесть, любовь, деньги, знания, бессмертие?.."
}