{
    "id": "6fmrHanHoX",
    "userId": "118049897850017649660-google",
    "createdAt": "2017-07-27 09:49:56",
    "updatedAt": "2017-07-27 09:49:56",
    "title": "Мечтают ли андроиды об электроовцах?",
    "author": "Филип Дик",
    "readDay": "4",
    "readMonth": "4",
    "readYear": "2017",
    "notes": "Плохо, очень плохо (нет, есть конечно и удачные моменты, но историю в целом они не спасают). В документальном фильме о съемках \"Бегущего\" один из интервьюируемых точно выразил мысль - \"как из ЭТОГО можно было сделать такой потрясающий фильм..?\"."
}