{
    "id": "6ml_F_dEXJ",
    "userId": "115753719718250012620-google",
    "createdAt": "2016-12-03 20:56:11",
    "updatedAt": "2016-12-03 20:56:11",
    "title": "Гордость и предубеждение",
    "author": "Остин, Джейн",
    "readDay": "3",
    "readMonth": "12",
    "readYear": "2016",
    "notes": "Великолепное произведение, по праву входящие практически во все рейтинге лучших книг. Отлично подмечены и описаны все абсурдные проблемы, вызванные предубежденным мнением и непомерной гордостью. И все это приправлено тонким английским юмором."
}